ShenruqianchuMfc/README.md
ShenruqianchuMfc/__init__.py
ShenruqianchuMfc/__main__.py
ShenruqianchuMfc/file.epub
ShenruqianchuMfc/index.html
ShenruqianchuMfc/css/__init__.py
ShenruqianchuMfc/css/annotations.css
ShenruqianchuMfc/css/main.css
ShenruqianchuMfc/css/normalize.css
ShenruqianchuMfc/css/popup.css
ShenruqianchuMfc/font/__init__.py
ShenruqianchuMfc/font/fontello.eot
ShenruqianchuMfc/font/fontello.svg
ShenruqianchuMfc/font/fontello.ttf
ShenruqianchuMfc/font/fontello.woff
ShenruqianchuMfc/img/__init__.py
ShenruqianchuMfc/img/annotator-glyph-sprite.png
ShenruqianchuMfc/img/annotator-icon-sprite.png
ShenruqianchuMfc/img/apple-touch-icon.png
ShenruqianchuMfc/img/cancelfullscreen.png
ShenruqianchuMfc/img/close.png
ShenruqianchuMfc/img/fullscreen.png
ShenruqianchuMfc/img/loader.gif
ShenruqianchuMfc/img/menu-icon.png
ShenruqianchuMfc/img/save.png
ShenruqianchuMfc/img/saved.png
ShenruqianchuMfc/img/settings-s.png
ShenruqianchuMfc/img/settings.png
ShenruqianchuMfc/img/star.png
ShenruqianchuMfc/js/__init__.py
ShenruqianchuMfc/js/epub.js
ShenruqianchuMfc/js/epub.min.js
ShenruqianchuMfc/js/epub.min.map
ShenruqianchuMfc/js/hooks.min.js
ShenruqianchuMfc/js/hooks.min.map
ShenruqianchuMfc/js/reader.js
ShenruqianchuMfc/js/reader.js.map
ShenruqianchuMfc/js/reader.min.js
ShenruqianchuMfc/js/reader.min.map
ShenruqianchuMfc/js/hooks/__init__.py
ShenruqianchuMfc/js/hooks/extensions/__init__.py
ShenruqianchuMfc/js/hooks/extensions/highlight.js
ShenruqianchuMfc/js/libs/__init__.py
ShenruqianchuMfc/js/libs/jquery.min.js
ShenruqianchuMfc/js/libs/localforage.min.js
ShenruqianchuMfc/js/libs/screenfull.js
ShenruqianchuMfc/js/libs/screenfull.min.js
ShenruqianchuMfc/js/libs/zip.min.js
ShenruqianchuMfc/js/plugins/__init__.py
ShenruqianchuMfc/js/plugins/hypothesis.js
ShenruqianchuMfc/js/plugins/search.js
shenruqianchu_mfc-2024.3.1.0.dist-info/METADATA
shenruqianchu_mfc-2024.3.1.0.dist-info/WHEEL
shenruqianchu_mfc-2024.3.1.0.dist-info/entry_points.txt
shenruqianchu_mfc-2024.3.1.0.dist-info/top_level.txt
shenruqianchu_mfc-2024.3.1.0.dist-info/RECORD
